[
    {
        "key": "datr",
        "value": "YuTVaaF7kdLDiga5fp8NaR59",
        "domain": "facebook.com",
        "path": "/",
        "hostOnly": false,
        "creation": "2026-04-21T08:53:10.923Z",
        "lastAccessed": "2026-04-21T08:53:10.932Z"
    },
    {
        "key": "sb",
        "value": "YuTVaYRE0HKQp_f5ItnjZQnx",
        "domain": "facebook.com",
        "path": "/",
        "hostOnly": false,
        "creation": "2026-04-21T08:53:10.932Z",
        "lastAccessed": "2026-04-21T08:53:10.932Z"
    },
    {
        "key": "vpd",
        "value": "v1%3B688x360x2",
        "domain": "facebook.com",
        "path": "/",
        "hostOnly": false,
        "creation": "2026-04-21T08:53:10.932Z",
        "lastAccessed": "2026-04-21T08:53:10.932Z"
    },
    {
        "key": "ps_l",
        "value": "1",
        "domain": "facebook.com",
        "path": "/",
        "hostOnly": false,
        "creation": "2026-04-21T08:53:10.932Z",
        "lastAccessed": "2026-04-21T08:53:10.932Z"
    },
    {
        "key": "ps_n",
        "value": "1",
        "domain": "facebook.com",
        "path": "/",
        "hostOnly": false,
        "creation": "2026-04-21T08:53:10.932Z",
        "lastAccessed": "2026-04-21T08:53:10.932Z"
    },
    {
        "key": "dpr",
        "value": "2.1988937854766846",
        "domain": "facebook.com",
        "path": "/",
        "hostOnly": false,
        "creation": "2026-04-21T08:53:10.932Z",
        "lastAccessed": "2026-04-21T08:53:10.932Z"
    },
    {
        "key": "oo",
        "value": "v1",
        "domain": "facebook.com",
        "path": "/",
        "hostOnly": false,
        "creation": "2026-04-21T08:53:10.932Z",
        "lastAccessed": "2026-04-21T08:53:10.932Z"
    },
    {
        "key": "pas",
        "value": "61557563282685%3AijsnI9dj7v%2C61570763782074%3A6IUKOaZITQ%2C61570696730553%3ALYNo9Qx7iR",
        "domain": "facebook.com",
        "path": "/",
        "hostOnly": false,
        "creation": "2026-04-21T08:53:10.932Z",
        "lastAccessed": "2026-04-21T08:53:10.932Z"
    },
    {
        "key": "locale",
        "value": "vi_VN",
        "domain": "facebook.com",
        "path": "/",
        "hostOnly": false,
        "creation": "2026-04-21T08:53:10.932Z",
        "lastAccessed": "2026-04-21T08:53:10.932Z"
    },
    {
        "key": "m_pixel_ratio",
        "value": "2",
        "domain": "facebook.com",
        "path": "/",
        "hostOnly": false,
        "creation": "2026-04-21T08:53:10.932Z",
        "lastAccessed": "2026-04-21T08:53:10.932Z"
    },
    {
        "key": "wd",
        "value": "360x800",
        "domain": "facebook.com",
        "path": "/",
        "hostOnly": false,
        "creation": "2026-04-21T08:53:10.932Z",
        "lastAccessed": "2026-04-21T08:53:10.932Z"
    },
    {
        "key": "c_user",
        "value": "61570763782074",
        "domain": "facebook.com",
        "path": "/",
        "hostOnly": false,
        "creation": "2026-04-21T08:53:10.932Z",
        "lastAccessed": "2026-04-21T08:53:10.932Z"
    },
    {
        "key": "xs",
        "value": "46%3AIjtlvr0yUxCfQQ%3A2%3A1776761592%3A-1%3A-1",
        "domain": "facebook.com",
        "path": "/",
        "hostOnly": false,
        "creation": "2026-04-21T08:53:10.932Z",
        "lastAccessed": "2026-04-21T08:53:10.932Z"
    },
    {
        "key": "fr",
        "value": "1myfaMyyatg9LIdSt.AWfVAlvd7i5UNhnQz0-I_QMqamP1T-IkquQt_MIZ7MBGnvLdvho.Bp5gcE..AAA.0.0.Bp5zr9.AWfJ3AckN1r3qN7DNArpWeAyWyo",
        "domain": "facebook.com",
        "path": "/",
        "hostOnly": false,
        "creation": "2026-04-21T08:53:10.932Z",
        "lastAccessed": "2026-04-21T08:53:10.932Z"
    },
    {
        "key": "fbl_st",
        "value": "101218340%3BT%3A29612692",
        "domain": "facebook.com",
        "path": "/",
        "hostOnly": false,
        "creation": "2026-04-21T08:53:10.932Z",
        "lastAccessed": "2026-04-21T08:53:10.932Z"
    },
    {
        "key": "wl_cbv",
        "value": "v2%3Bclient_version%3A3148%3Btimestamp%3A1776761597",
        "domain": "facebook.com",
        "path": "/",
        "hostOnly": false,
        "creation": "2026-04-21T08:53:10.932Z",
        "lastAccessed": "2026-04-21T08:53:10.932Z"
    }
]
